synthetic_energy/__init__.py
synthetic_energy/configs.py
synthetic_energy/errors.py
synthetic_energy/gan.py
synthetic_energy/logger.py
synthetic_energy/schemas.py
synthetic_energy/synthesiser.py
synthetic_energy/utils.py
synthetic_energy/anonymization/__init__.py
synthetic_energy/anonymization/anonymizer.py
synthetic_energy/anonymization/schemas.py
synthetic_energy/anonymization/classifiers/__init__.py
synthetic_energy/anonymization/classifiers/classifier.py
synthetic_energy/anonymization/classifiers/create_dataset.py
synthetic_energy/anonymization/classifiers/labeler_encoder.pkl
synthetic_energy/anonymization/classifiers/multi_column_classifier.pkl
synthetic_energy/anonymization/classifiers/scaler.pkl
synthetic_energy/anonymization/classifiers/train_classifier.py
synthetic_energy/attacks/__init__.py
synthetic_energy/attacks/base.py
synthetic_energy/attacks/carlini_wagner_attack/__init__.py
synthetic_energy/attacks/carlini_wagner_attack/carlini_wagner_attack.py
synthetic_energy/attacks/fast_gradient_sign_attack/__init__.py
synthetic_energy/attacks/fast_gradient_sign_attack/fast_gradient_sign_attack.py
synthetic_energy/attacks/membership_inference_attack/__init__.py
synthetic_energy/attacks/membership_inference_attack/membership_inference_attack.py
synthetic_energy/attacks/projected_gradient_descent_attack/__init__.py
synthetic_energy/attacks/projected_gradient_descent_attack/projected_gradient_descent_attack.py
synthetic_energy/defenses/__init__.py
synthetic_energy/defenses/differential_privacy/__init__.py
synthetic_energy/defenses/differential_privacy/differential_privacy.py
synthetic_energy/quality_metrics/__init__.py
synthetic_energy/quality_metrics/kl_divergence.py
synthetic_energy/tabular/__init__.py
synthetic_energy/tabular/actgan/__init__.py
synthetic_energy/tabular/actgan/actgan.py
synthetic_energy/tabular/actgan/base.py
synthetic_energy/tabular/actgan/column_encodings.py
synthetic_energy/tabular/actgan/columnar_df.py
synthetic_energy-0.0.15.dist-info/LICENSE
synthetic_energy-0.0.15.dist-info/METADATA
synthetic_energy-0.0.15.dist-info/WHEEL
synthetic_energy-0.0.15.dist-info/top_level.txt
synthetic_energy-0.0.15.dist-info/RECORD
