Metadata-Version: 2.1
Name: synthetic_energy
Version: 0.0.15
Summary: PhD work for ICSP @ FEUP, PORTO
Author: Rui Melo & André Catarino
Author-email: rufimelo99@gmail.com; andre.almeida.catarino@gmail.com
Classifier: Programming Language :: Python :: 3
Classifier: License :: OSI Approved :: GNU General Public License v3 (GPLv3)
Classifier: Operating System :: OS Independent
Requires-Python: >=3.10
License-File: LICENSE
Requires-Dist: category_encoders>=2.6.3
Requires-Dist: torch>=2.2.2
Requires-Dist: scikit-learn>=1.5.1
Requires-Dist: visions>=0.7.6
Requires-Dist: ImageHash>=4.3.1
Requires-Dist: shapely>=2.0.5
Requires-Dist: pytest>=2.0.1
Requires-Dist: rdt>=1.12.2
Requires-Dist: spacy>=3.7.5
Requires-Dist: faker
Requires-Dist: structlog
